scia/__init__.py
scia/_version.py
scia/add_dummy_variables.py
scia/as_data_frame.py
scia/autocorr.py
scia/bayesplm.py
scia/bayesplm.py.BK
scia/bk_tau_u.py.bk
scia/check_args.py
scia/check_scdf.py
scia/core.py
scia/corrected_tau.py
scia/create_dummies.py
scia/create_fixed_formula.py
scia/create_phase_dummies.py
scia/create_random_formula.py
scia/create_slope_dummies.py
scia/data.py
scia/describe.py
scia/fill_missing.py
scia/filter.py
scia/hplm.py
scia/io.py
scia/ird.py
scia/mplm.py
scia/nap.py
scia/overlap.py
scia/pand.py
scia/pem.py
scia/pet.py
scia/phasestructure.py
scia/plm.py
scia/plot.py
scia/pnd.py
scia/prepare_scdf.py
scia/preprocess.py
scia/print_hplm.py
scia/rci.py
scia/recombine.py
scia/rename_phase_duplicates.py
scia/select.py
scia/smd.py
scia/std_lm.py
scia/summary.py
scia/tau_u.py
scia/trimws.py
scia/unlist.py
scia/utils.py
scia-2.1.1.dist-info/licenses/LICENSE
scia-2.1.1.dist-info/METADATA
scia-2.1.1.dist-info/WHEEL
scia-2.1.1.dist-info/top_level.txt
scia-2.1.1.dist-info/RECORD
