Metadata-Version: 2.4
Name: scia
Version: 2.1.1
Summary: A Comprehensive most updated Python package for Single Case Design Analysis
Home-page: https://github.com/AhsanKhodami/scia
Author: Mohammad Ahsan Khodami
Author-email: ahsan.khodami@gmail.com
Classifier: Programming Language :: Python :: 3
Classifier: License :: OSI Approved :: MIT License
Classifier: Operating System :: OS Independent
Requires-Python: >=3.9
License-File: LICENSE
Requires-Dist: numpy
Requires-Dist: pandas
Requires-Dist: matplotlib
Requires-Dist: scipy
Requires-Dist: openpyxl
Requires-Dist: scikit-learn
Requires-Dist: statsmodels
Dynamic: author
Dynamic: author-email
Dynamic: classifier
Dynamic: description
Dynamic: description-content-type
Dynamic: home-page
Dynamic: license-file
Dynamic: requires-dist
Dynamic: requires-python
Dynamic: summary
